procurement_bytetheory/__init__.py
procurement_bytetheory/controllers/CLIController.py
procurement_bytetheory/controllers/Observer.py
procurement_bytetheory/controllers/UIController.py
procurement_bytetheory/controllers/__init__.py
procurement_bytetheory/data/ProcurementGame.db
procurement_bytetheory/data/__init__.py
procurement_bytetheory/data/items.csv
procurement_bytetheory/db_connectors/BusinessDbHandler.py
procurement_bytetheory/db_connectors/DatabaseHandler.py
procurement_bytetheory/db_connectors/InventoryDbHandler.py
procurement_bytetheory/db_connectors/ItemDbHandler.py
procurement_bytetheory/db_connectors/MarketDbHandler.py
procurement_bytetheory/db_connectors/__init__.py
procurement_bytetheory/errors/InsufficientFundsError.py
procurement_bytetheory/errors/__init__.py
procurement_bytetheory/model/Business.py
procurement_bytetheory/model/Inventory.py
procurement_bytetheory/model/Item.py
procurement_bytetheory/model/Market.py
procurement_bytetheory/model/Subject.py
procurement_bytetheory/model/__init__.py
procurement_bytetheory/utils/FloatValidator.py
procurement_bytetheory/utils/__init__.py
procurement_bytetheory/views/CLIProcurementGame.py
procurement_bytetheory/views/CLIProcurementSimulator.py
procurement_bytetheory/views/__init__.py
procurement_bytetheory-1.0.17.dist-info/LICENSE
procurement_bytetheory-1.0.17.dist-info/METADATA
procurement_bytetheory-1.0.17.dist-info/WHEEL
procurement_bytetheory-1.0.17.dist-info/top_level.txt
procurement_bytetheory-1.0.17.dist-info/RECORD
