Metadata-Version: 2.1
Name: procurement-bytetheory
Version: 1.0.17
Summary: Provides helpers to procurement app.
Author: Robbie Blom
Classifier: Programming Language :: Python :: 3
Classifier: License :: OSI Approved :: MIT License
Classifier: Operating System :: OS Independent
Requires-Python: >=3.6
License-File: LICENSE
